dash_callbackmanager/__init__.py
dash_callbackmanager/manager.py
dash_callbackmanager/tests/test_callbackmanager.py
dash_callbackmanager-2.0.0.dist-info/LICENSE
dash_callbackmanager-2.0.0.dist-info/WHEEL
dash_callbackmanager-2.0.0.dist-info/METADATA
dash_callbackmanager-2.0.0.dist-info/RECORD
